bifrostx-0.1.21.dist-info/METADATA
bifrostx-0.1.21.dist-info/WHEEL
bifrostx-0.1.21.dist-info/entry_points.txt
bifrostx/__init__.py
bifrostx/adapter/__init__.py
bifrostx/adapter/profile.py
bifrostx/adapter/register.py
bifrostx/cli.py
bifrostx/component/__init__.py
bifrostx/component/base.py
bifrostx/component/profile.py
bifrostx/component/register.py
bifrostx/config.py
bifrostx/core/__init__.py
bifrostx/core/data_model.py
bifrostx/core/profile.py
bifrostx/initialization.py
bifrostx/interface/__init__.py
bifrostx/interface/base.py
bifrostx/interface/profile.py
bifrostx/interface/register.py
bifrostx/server.py
bifrostx/utils/__init__.py
bifrostx/utils/logger.py
bifrostx-0.1.21.dist-info/RECORD
