Metadata-Version: 2.1
Name: BifrostX
Version: 0.1.21
Summary: BifrostX - Intelligent Assembling, Unlimited Possibilities!
Author-Email: Bevis <alonefire@foxmail.com>
License: MIT
Project-URL: Homepage, https://github.com/AloneFire/BifrostX
Project-URL: Bug tracker, https://github.com/AloneFire/BifrostX/issues
Requires-Python: >=3.9
Requires-Dist: pydantic>=2.4.2
Requires-Dist: loguru>=0.7.2
Requires-Dist: pydantic-settings>=2.0.3
Requires-Dist: fastapi>=0.104.1
Requires-Dist: click>=8.1.7
Requires-Dist: hypercorn>=0.15.0
